Metadata-Version: 2.1
Name: increase-recursionlimit
Version: 1.0.0
Summary: Context manager to increase a recursionlimit.
Home-page: https://github.com/kavigupta/increase-recursionlimit
Author: Kavi Gupta
Author-email: kavig+increase_recursionlimit@mit.edu
Classifier: Programming Language :: Python :: 3.7
Classifier: Programming Language :: Python :: 3.8
Classifier: Programming Language :: Python :: 3.9
Classifier: Programming Language :: Python :: 3.10
Classifier: Programming Language :: Python :: 3.11
Classifier: Operating System :: OS Independent
Requires-Python: >=3.7
